aiokafka_agent/__init__.py
aiokafka_agent/broker/__init__.py
aiokafka_agent/broker/kafka/__init__.py
aiokafka_agent/broker/kafka/client.py
aiokafka_agent/broker/kafka/config.py
aiokafka_agent/broker/kafka/producer.py
aiokafka_agent/broker/kafka/serializer.py
aiokafka_agent/broker/kafka/time_limit.py
aiokafka_agent/broker/kafka/topic_info.py
aiokafka_agent/broker/kafka/consumer/__init__.py
aiokafka_agent/broker/kafka/consumer/app.py
aiokafka_agent/broker/kafka/consumer/dispatcher.py
aiokafka_agent/broker/kafka/consumer/lifecycle.py
aiokafka_agent/broker/kafka/consumer/metadata.py
aiokafka_agent/broker/kafka/consumer/partition.py
aiokafka_agent/broker/kafka/consumer/reballance_listner.py
aiokafka_agent/broker/kafka/consumer/schemas.py
aiokafka_agent/broker/kafka/consumer/types.py
aiokafka_agent/broker/kafka/consumer/descriptor/__init__.py
aiokafka_agent/broker/kafka/consumer/descriptor/stream.py
aiokafka_agent/infra/__init__.py
aiokafka_agent/infra/asyncio/__init__.py
aiokafka_agent/infra/asyncio/config.py
aiokafka_agent/infra/asyncio/event_loop.py
aiokafka_agent/infra/asyncio/none.py
aiokafka_agent/infra/asyncio/threading.py
aiokafka_agent/infra/asyncio/time_limit.py
aiokafka_agent/infra/asyncio/wrapper.py
aiokafka_agent/infra/context/__init__.py
aiokafka_agent/infra/context/globals.py
aiokafka_agent/infra/context/types.py
aiokafka_agent/infra/datatype/__init__.py
aiokafka_agent/infra/datatype/cast.py
aiokafka_agent/infra/datatype/json.py
aiokafka_agent/infra/datatype/list.py
aiokafka_agent/infra/datatype/singleton.py
aiokafka_agent/infra/datatype/string.py
aiokafka_agent/infra/datatype/timedelta.py
aiokafka_agent/infra/datatype/types.py
aiokafka_agent/infra/logger/__init__.py
aiokafka_agent/infra/logger/decorator.py
aiokafka_agent/infra/logger/main.py
aiokafka_agent/infra/probe/__init__.py
aiokafka_agent/infra/probe/config.py
aiokafka_agent/infra/probe/liveness.py
aiokafka_agent-0.1.4.dist-info/METADATA
aiokafka_agent-0.1.4.dist-info/WHEEL
aiokafka_agent-0.1.4.dist-info/top_level.txt
aiokafka_agent-0.1.4.dist-info/RECORD
