Metadata-Version: 2.4
Name: aiokafka-agent
Version: 0.1.4
Requires-Python: >=3.9
Requires-Dist: aiokafka
Requires-Dist: pydantic>=2.0.0
Requires-Dist: pydantic-settings>=2.0.0
Dynamic: requires-dist
Dynamic: requires-python
